biotmed_measurement_sdk/__init__.py
biotmed_measurement_sdk/api_client.py
biotmed_measurement_sdk/api_response.py
biotmed_measurement_sdk/configuration.py
biotmed_measurement_sdk/exceptions.py
biotmed_measurement_sdk/py.typed
biotmed_measurement_sdk/rest.py
biotmed_measurement_sdk/api/__init__.py
biotmed_measurement_sdk/api/health_check_api_api.py
biotmed_measurement_sdk/api/measurements_api_api.py
biotmed_measurement_sdk/api/measurements_v2_api_api.py
biotmed_measurement_sdk/models/__init__.py
biotmed_measurement_sdk/models/error_response.py
biotmed_measurement_sdk/models/failed_measurement_message_from_device.py
biotmed_measurement_sdk/models/failure_data.py
biotmed_measurement_sdk/models/filter_v2.py
biotmed_measurement_sdk/models/get_aggregated_measurements_response.py
biotmed_measurement_sdk/models/get_raw_measurements_response.py
biotmed_measurement_sdk/models/measurement.py
biotmed_measurement_sdk/models/measurement_aggregation_data.py
biotmed_measurement_sdk/models/measurement_attributes.py
biotmed_measurement_sdk/models/measurement_bulk_metadata.py
biotmed_measurement_sdk/models/measurement_bulk_request.py
biotmed_measurement_sdk/models/measurement_bulk_response.py
biotmed_measurement_sdk/models/measurement_data_schema_example.py
biotmed_measurement_sdk/models/measurement_from_device_metadata.py
biotmed_measurement_sdk/models/measurement_message_from_device.py
biotmed_measurement_sdk/models/measurement_raw_attributes.py
biotmed_measurement_sdk/models/measurement_raw_source.py
biotmed_measurement_sdk/models/measurement_session.py
biotmed_measurement_sdk/models/measurement_source.py
biotmed_measurement_sdk/models/measurements_aggregation_data_v2.py
biotmed_measurement_sdk/models/metadata_token_based.py
biotmed_measurement_sdk/models/order.py
biotmed_measurement_sdk/models/raw_measurement.py
biotmed_measurement_sdk/models/raw_measurement_sessions.py
biotmed_measurement_sdk/models/raw_measurement_v2.py
biotmed_measurement_sdk-2.3.40.dist-info/METADATA
biotmed_measurement_sdk-2.3.40.dist-info/WHEEL
biotmed_measurement_sdk-2.3.40.dist-info/top_level.txt
biotmed_measurement_sdk-2.3.40.dist-info/RECORD
